pyslise2d.cpython-39-darwin.so
pyslise2d-0.0.1.dist-info/METADATA
pyslise2d-0.0.1.dist-info/WHEEL
pyslise2d-0.0.1.dist-info/top_level.txt
pyslise2d-0.0.1.dist-info/RECORD
