Metadata-Version: 2.1
Name: pyslise2d
Version: 0.0.1
Summary: Python bindings for the C++ version of 2D Matslise
Home-page: https://matslise.ugent.be/
Author: Toon Baeyens
Author-email: toon.baeyens@ugent.be
License: UNKNOWN
Platform: UNKNOWN
Requires-Dist: numpy
